zenkai/__init__.py
zenkai/ensemble/__init__.py
zenkai/ensemble/_ensemble.py
zenkai/ensemble/_ensemble_mod.py
zenkai/feedback/__init__.py
zenkai/feedback/_feedback_alignment.py
zenkai/kaku/__init__.py
zenkai/kaku/_assess.py
zenkai/kaku/_grad.py
zenkai/kaku/_io2.py
zenkai/kaku/_iterable.py
zenkai/kaku/_limit.py
zenkai/kaku/_lm2.py
zenkai/kaku/_lm_assess.py
zenkai/kaku/_null.py
zenkai/kaku/_objective.py
zenkai/kaku/_optimize.py
zenkai/kaku/_state.py
zenkai/scikit/__init__.py
zenkai/scikit/_scikit.py
zenkai/scikit/_scikit_mod.py
zenkai/tansaku/__init__.py
zenkai/tansaku/_aggregate.py
zenkai/tansaku/_constraints.py
zenkai/tansaku/_crossover.py
zenkai/tansaku/_evolutionary.py
zenkai/tansaku/_module.py
zenkai/tansaku/_noise.py
zenkai/tansaku/_optim.py
zenkai/tansaku/_params.py
zenkai/tansaku/_reshape.py
zenkai/tansaku/_selection.py
zenkai/tansaku/_update.py
zenkai/tansaku/_weight.py
zenkai/targetprop/__init__.py
zenkai/targetprop/_least_squares.py
zenkai/targetprop/_reversible.py
zenkai/targetprop/_reversible_mods.py
zenkai/targetprop/_target_prop.py
zenkai/utils/__init__.py
zenkai/utils/_build.py
zenkai/utils/_convert.py
zenkai/utils/_memory.py
zenkai/utils/_params.py
zenkai/utils/_ste.py
zenkai-0.0.9.dist-info/LICENSE
zenkai-0.0.9.dist-info/METADATA
zenkai-0.0.9.dist-info/WHEEL
zenkai-0.0.9.dist-info/RECORD
