Metadata-Version: 2.1
Name: zenkai
Version: 0.0.9
Summary: A framework for flexibly developing beyond bakcpropagation.
Home-page: https://github.com/short-greg/zenkai
License: LICENSE
Author: Greg Short
Author-email: g.short@kurenai.waseda.jp
Requires-Python: >=3.8,<4.0
Classifier: License :: Other/Proprietary License
Classifier: Programming Language :: Python :: 3
Classifier: Programming Language :: Python :: 3.8
Classifier: Programming Language :: Python :: 3.9
Classifier: Programming Language :: Python :: 3.10
Classifier: Programming Language :: Python :: 3.11
Classifier: Programming Language :: Python :: 3.12
Requires-Dist: numpy (>=1)
Requires-Dist: pandas (>=1)
Requires-Dist: scikit-learn (>=1.0.0)
Requires-Dist: scipy (>=1.5)
Requires-Dist: tqdm (>=4.0)
Project-URL: Documentation, https://zenkai.readthedocs.com
Project-URL: Repository, https://github.com/short-greg/zenkai
